{
  "/_astro/1-about.DwLlX6X__1p8tlC.webp": "988ece44",
  "/_astro/jp-learning-1.JLOdRc7B_3Nk3Q.webp": "777111bb",
  "/_astro/jp-learning-2.DHdxU59W_ZlAjNG.webp": "88933244",
  "/_astro/jp-learning-3.DiETq6Rs_Z134lUR.webp": "764ecd19",
  "/_astro/01-life_lately-SDV.VWA767DW_ZVl6kY.webp": "22508632",
  "/_astro/01-life_lately-dia.wZkWonBL_Z7QYp2.webp": "544c8a2a",
  "/_astro/01-life_lately-flowers.CpSSvA7r_ZeCINU.webp": "986ea91a",
  "/_astro/01-life_lately-cafe.DaXVcvH9_Z22lyRm.webp": "865311a1",
  "/_astro/01-life_lately-sunset.CCIvfl5F_1npEBY.webp": "9ab30c91"
}
